{"ele": "545", "carper": "1", "md": "E", "t": "2", "f": "O", "esae": "N", "mnae": " ", "dg": "31/10/2022", "hg": "00:29:42", "dv": "S", "nadf": "am-c0001-e000545-001-f", "abr": [{"dt": "30/10/2022", "ht": "19:54:10", "tf": "S", "and": "F", "tpabr": "MU", "cdabr": "02070", "s": "85", "st": "85", "snt": "0", "si": "85", "sni": "0", "sa": "85", "sna": "0", "pst": "100,00", "psnt": "0,00", "psi": "100,00", "psni": "0,00", "psa": "100,00", "psna": "0,00", "e": "28954", "ea": "28954", "ena": "0", "esi": "28954", "esni": "0", "c": "20127", "a": "8827", "pea": "100,00", "pena": "0,00", "pesi": "100,00", "pesni": "0,00", "pa": "30,49", "pc": "69,51", "vscv": "0", "vnom": "19089", "tv": "20127", "vvc": "19089", "vb": "129", "tvn": "909", "vn": "909", "vnt": "0", "vp": "0", "vv": "19089", "van": "0", "vansj": "0", "pvnom": "100,00", "pvvc": "94,84", "pvb": "0,64", "ptvn": "4,52", "pvn": "100,00", "pvnt": "0,00", "pvp": "0,00", "pvv": "100,00", "pvan": "0,00", "pvansj": "0,00", "cand": [{"seq": "1", "n": "13", "vap": "12283", "pvap": "64,35", "e": "S", "st": "Eleito"}, {"seq": "2", "n": "22", "vap": "6806", "pvap": "35,65", "e": "N", "st": "N\u00e3o eleito"}]}, {"dt": "30/10/2022", "ht": "19:54:10", "tf": "S", "and": "F", "tpabr": "ZONA", "cdabr": "35", "s": "85", "st": "85", "snt": "0", "si": "85", "sni": "0", "sa": "85", "sna": "0", "pst": "100,00", "psnt": "0,00", "psi": "100,00", "psni": "0,00", "psa": "100,00", "psna": "0,00", "e": "28954", "ea": "28954", "ena": "0", "esi": "28954", "esni": "0", "a": "8827", "c": "20127", "pea": "100,00", "pena": "0,00", "pesi": "100,00", "pesni": "0,00", "pa": "30,49", "pc": "69,51", "vnom": "19089", "vscv": "0", "tv": "20127", "vvc": "19089", "vb": "129", "tvn": "909", "vn": "909", "vnt": "0", "vp": "0", "vv": "19089", "van": "0", "vansj": "0", "pvnom": "100,00", "pvvc": "94,84", "pvb": "0,64", "ptvn": "4,52", "pvn": "100,00", "pvnt": "0,00", "pvp": "0,00", "pvv": "100,00", "pvan": "0,00", "pvansj": "0,00", "cand": [{"seq": "1", "n": "13", "vap": "12283", "pvap": "64,35", "e": "S", "st": "Eleito"}, {"seq": "2", "n": "22", "vap": "6806", "pvap": "35,65", "e": "N", "st": "N\u00e3o eleito"}]}]}