{"ele": "545", "carper": "1", "md": "E", "t": "2", "f": "O", "esae": "N", "mnae": " ", "dg": "31/10/2022", "hg": "00:29:43", "dv": "S", "nadf": "am-c0001-e000545-001-f", "abr": [{"dt": "30/10/2022", "ht": "16:47:24", "tf": "S", "and": "F", "tpabr": "MU", "cdabr": "02470", "s": "27", "st": "27", "snt": "0", "si": "27", "sni": "0", "sa": "27", "sna": "0", "pst": "100,00", "psnt": "0,00", "psi": "100,00", "psni": "0,00", "psa": "100,00", "psna": "0,00", "e": "7874", "ea": "7874", "ena": "0", "esi": "7874", "esni": "0", "c": "5021", "a": "2853", "pea": "100,00", "pena": "0,00", "pesi": "100,00", "pesni": "0,00", "pa": "36,23", "pc": "63,77", "vscv": "0", "vnom": "4671", "tv": "5021", "vvc": "4671", "vb": "67", "tvn": "283", "vn": "283", "vnt": "0", "vp": "0", "vv": "4671", "van": "0", "vansj": "0", "pvnom": "100,00", "pvvc": "93,03", "pvb": "1,33", "ptvn": "5,64", "pvn": "100,00", "pvnt": "0,00", "pvp": "0,00", "pvv": "100,00", "pvan": "0,00", "pvansj": "0,00", "cand": [{"seq": "1", "n": "13", "vap": "2870", "pvap": "61,44", "e": "S", "st": "Eleito"}, {"seq": "2", "n": "22", "vap": "1801", "pvap": "38,56", "e": "N", "st": "N\u00e3o eleito"}]}, {"dt": "30/10/2022", "ht": "16:47:24", "tf": "S", "and": "F", "tpabr": "ZONA", "cdabr": "50", "s": "27", "st": "27", "snt": "0", "si": "27", "sni": "0", "sa": "27", "sna": "0", "pst": "100,00", "psnt": "0,00", "psi": "100,00", "psni": "0,00", "psa": "100,00", "psna": "0,00", "e": "7874", "ea": "7874", "ena": "0", "esi": "7874", "esni": "0", "a": "2853", "c": "5021", "pea": "100,00", "pena": "0,00", "pesi": "100,00", "pesni": "0,00", "pa": "36,23", "pc": "63,77", "vnom": "4671", "vscv": "0", "tv": "5021", "vvc": "4671", "vb": "67", "tvn": "283", "vn": "283", "vnt": "0", "vp": "0", "vv": "4671", "van": "0", "vansj": "0", "pvnom": "100,00", "pvvc": "93,03", "pvb": "1,33", "ptvn": "5,64", "pvn": "100,00", "pvnt": "0,00", "pvp": "0,00", "pvv": "100,00", "pvan": "0,00", "pvansj": "0,00", "cand": [{"seq": "1", "n": "13", "vap": "2870", "pvap": "61,44", "e": "S", "st": "Eleito"}, {"seq": "2", "n": "22", "vap": "1801", "pvap": "38,56", "e": "N", "st": "N\u00e3o eleito"}]}]}