{"ele": "545", "carper": "1", "md": "E", "t": "2", "f": "O", "esae": "N", "mnae": " ", "dg": "31/10/2022", "hg": "00:29:44", "dv": "S", "nadf": "am-c0001-e000545-001-f", "abr": [{"dt": "30/10/2022", "ht": "17:36:09", "tf": "S", "and": "F", "tpabr": "MU", "cdabr": "02950", "s": "38", "st": "38", "snt": "0", "si": "38", "sni": "0", "sa": "38", "sna": "0", "pst": "100,00", "psnt": "0,00", "psi": "100,00", "psni": "0,00", "psa": "100,00", "psna": "0,00", "e": "13827", "ea": "13827", "ena": "0", "esi": "13827", "esni": "0", "c": "8998", "a": "4829", "pea": "100,00", "pena": "0,00", "pesi": "100,00", "pesni": "0,00", "pa": "34,92", "pc": "65,08", "vscv": "0", "vnom": "8539", "tv": "8998", "vvc": "8539", "vb": "61", "tvn": "398", "vn": "398", "vnt": "0", "vp": "0", "vv": "8539", "van": "0", "vansj": "0", "pvnom": "100,00", "pvvc": "94,90", "pvb": "0,68", "ptvn": "4,42", "pvn": "100,00", "pvnt": "0,00", "pvp": "0,00", "pvv": "100,00", "pvan": "0,00", "pvansj": "0,00", "cand": [{"seq": "1", "n": "13", "vap": "5381", "pvap": "63,02", "e": "S", "st": "Eleito"}, {"seq": "2", "n": "22", "vap": "3158", "pvap": "36,98", "e": "N", "st": "N\u00e3o eleito"}]}, {"dt": "30/10/2022", "ht": "17:36:09", "tf": "S", "and": "F", "tpabr": "ZONA", "cdabr": "54", "s": "38", "st": "38", "snt": "0", "si": "38", "sni": "0", "sa": "38", "sna": "0", "pst": "100,00", "psnt": "0,00", "psi": "100,00", "psni": "0,00", "psa": "100,00", "psna": "0,00", "e": "13827", "ea": "13827", "ena": "0", "esi": "13827", "esni": "0", "a": "4829", "c": "8998", "pea": "100,00", "pena": "0,00", "pesi": "100,00", "pesni": "0,00", "pa": "34,92", "pc": "65,08", "vnom": "8539", "vscv": "0", "tv": "8998", "vvc": "8539", "vb": "61", "tvn": "398", "vn": "398", "vnt": "0", "vp": "0", "vv": "8539", "van": "0", "vansj": "0", "pvnom": "100,00", "pvvc": "94,90", "pvb": "0,68", "ptvn": "4,42", "pvn": "100,00", "pvnt": "0,00", "pvp": "0,00", "pvv": "100,00", "pvan": "0,00", "pvansj": "0,00", "cand": [{"seq": "1", "n": "13", "vap": "5381", "pvap": "63,02", "e": "S", "st": "Eleito"}, {"seq": "2", "n": "22", "vap": "3158", "pvap": "36,98", "e": "N", "st": "N\u00e3o eleito"}]}]}