{"ele": "545", "carper": "1", "md": "E", "t": "2", "f": "O", "esae": "N", "mnae": " ", "dg": "31/10/2022", "hg": "00:29:45", "dv": "S", "nadf": "mg-c0001-e000545-002-f", "abr": [{"dt": "30/10/2022", "ht": "18:44:32", "tf": "S", "and": "F", "tpabr": "MU", "cdabr": "42250", "s": "29", "st": "29", "snt": "0", "si": "29", "sni": "0", "sa": "29", "sna": "0", "pst": "100,00", "psnt": "0,00", "psi": "100,00", "psni": "0,00", "psa": "100,00", "psna": "0,00", "e": "10099", "ea": "10099", "ena": "0", "esi": "10099", "esni": "0", "c": "7844", "a": "2255", "pea": "100,00", "pena": "0,00", "pesi": "100,00", "pesni": "0,00", "pa": "22,33", "pc": "77,67", "vscv": "0", "vnom": "7533", "tv": "7844", "vvc": "7533", "vb": "148", "tvn": "163", "vn": "163", "vnt": "0", "vp": "0", "vv": "7533", "van": "0", "vansj": "0", "pvnom": "100,00", "pvvc": "96,04", "pvb": "1,88", "ptvn": "2,08", "pvn": "100,00", "pvnt": "0,00", "pvp": "0,00", "pvv": "100,00", "pvan": "0,00", "pvansj": "0,00", "cand": [{"seq": "1", "n": "13", "vap": "4481", "pvap": "59,48", "e": "S", "st": "Eleito"}, {"seq": "2", "n": "22", "vap": "3052", "pvap": "40,52", "e": "N", "st": "N\u00e3o eleito"}]}, {"dt": "30/10/2022", "ht": "18:44:32", "tf": "S", "and": "F", "tpabr": "ZONA", "cdabr": "65", "s": "29", "st": "29", "snt": "0", "si": "29", "sni": "0", "sa": "29", "sna": "0", "pst": "100,00", "psnt": "0,00", "psi": "100,00", "psni": "0,00", "psa": "100,00", "psna": "0,00", "e": "10099", "ea": "10099", "ena": "0", "esi": "10099", "esni": "0", "a": "2255", "c": "7844", "pea": "100,00", "pena": "0,00", "pesi": "100,00", "pesni": "0,00", "pa": "22,33", "pc": "77,67", "vnom": "7533", "vscv": "0", "tv": "7844", "vvc": "7533", "vb": "148", "tvn": "163", "vn": "163", "vnt": "0", "vp": "0", "vv": "7533", "van": "0", "vansj": "0", "pvnom": "100,00", "pvvc": "96,04", "pvb": "1,88", "ptvn": "2,08", "pvn": "100,00", "pvnt": "0,00", "pvp": "0,00", "pvv": "100,00", "pvan": "0,00", "pvansj": "0,00", "cand": [{"seq": "1", "n": "13", "vap": "4481", "pvap": "59,48", "e": "S", "st": "Eleito"}, {"seq": "2", "n": "22", "vap": "3052", "pvap": "40,52", "e": "N", "st": "N\u00e3o eleito"}]}]}