{"ele": "545", "carper": "1", "md": "E", "t": "2", "f": "O", "esae": "N", "mnae": " ", "dg": "31/10/2022", "hg": "00:29:47", "dv": "S", "nadf": "mg-c0001-e000545-002-f", "abr": [{"dt": "30/10/2022", "ht": "19:13:31", "tf": "S", "and": "F", "tpabr": "MU", "cdabr": "44679", "s": "6", "st": "6", "snt": "0", "si": "6", "sni": "0", "sa": "6", "sna": "0", "pst": "100,00", "psnt": "0,00", "psi": "100,00", "psni": "0,00", "psa": "100,00", "psna": "0,00", "e": "2263", "ea": "2263", "ena": "0", "esi": "2263", "esni": "0", "c": "1587", "a": "676", "pea": "100,00", "pena": "0,00", "pesi": "100,00", "pesni": "0,00", "pa": "29,87", "pc": "70,13", "vscv": "0", "vnom": "1541", "tv": "1587", "vvc": "1541", "vb": "22", "tvn": "24", "vn": "24", "vnt": "0", "vp": "0", "vv": "1541", "van": "0", "vansj": "0", "pvnom": "100,00", "pvvc": "97,10", "pvb": "1,39", "ptvn": "1,51", "pvn": "100,00", "pvnt": "0,00", "pvp": "0,00", "pvv": "100,00", "pvan": "0,00", "pvansj": "0,00", "cand": [{"seq": "1", "n": "13", "vap": "733", "pvap": "47,57", "e": "S", "st": "Eleito"}, {"seq": "2", "n": "22", "vap": "808", "pvap": "52,43", "e": "N", "st": "N\u00e3o eleito"}]}, {"dt": "30/10/2022", "ht": "19:13:31", "tf": "S", "and": "F", "tpabr": "ZONA", "cdabr": "220", "s": "6", "st": "6", "snt": "0", "si": "6", "sni": "0", "sa": "6", "sna": "0", "pst": "100,00", "psnt": "0,00", "psi": "100,00", "psni": "0,00", "psa": "100,00", "psna": "0,00", "e": "2263", "ea": "2263", "ena": "0", "esi": "2263", "esni": "0", "a": "676", "c": "1587", "pea": "100,00", "pena": "0,00", "pesi": "100,00", "pesni": "0,00", "pa": "29,87", "pc": "70,13", "vnom": "1541", "vscv": "0", "tv": "1587", "vvc": "1541", "vb": "22", "tvn": "24", "vn": "24", "vnt": "0", "vp": "0", "vv": "1541", "van": "0", "vansj": "0", "pvnom": "100,00", "pvvc": "97,10", "pvb": "1,39", "ptvn": "1,51", "pvn": "100,00", "pvnt": "0,00", "pvp": "0,00", "pvv": "100,00", "pvan": "0,00", "pvansj": "0,00", "cand": [{"seq": "1", "n": "13", "vap": "733", "pvap": "47,57", "e": "S", "st": "Eleito"}, {"seq": "2", "n": "22", "vap": "808", "pvap": "52,43", "e": "N", "st": "N\u00e3o eleito"}]}]}