{"ele": "545", "carper": "1", "md": "E", "t": "2", "f": "O", "esae": "N", "mnae": " ", "dg": "31/10/2022", "hg": "00:29:47", "dv": "S", "nadf": "mg-c0001-e000545-002-f", "abr": [{"dt": "30/10/2022", "ht": "21:19:21", "tf": "S", "and": "F", "tpabr": "MU", "cdabr": "46795", "s": "40", "st": "40", "snt": "0", "si": "40", "sni": "0", "sa": "40", "sna": "0", "pst": "100,00", "psnt": "0,00", "psi": "100,00", "psni": "0,00", "psa": "100,00", "psna": "0,00", "e": "11263", "ea": "11263", "ena": "0", "esi": "11263", "esni": "0", "c": "7853", "a": "3410", "pea": "100,00", "pena": "0,00", "pesi": "100,00", "pesni": "0,00", "pa": "30,28", "pc": "69,72", "vscv": "0", "vnom": "7612", "tv": "7853", "vvc": "7612", "vb": "70", "tvn": "171", "vn": "171", "vnt": "0", "vp": "0", "vv": "7612", "van": "0", "vansj": "0", "pvnom": "100,00", "pvvc": "96,93", "pvb": "0,89", "ptvn": "2,18", "pvn": "100,00", "pvnt": "0,00", "pvp": "0,00", "pvv": "100,00", "pvan": "0,00", "pvansj": "0,00", "cand": [{"seq": "1", "n": "13", "vap": "5944", "pvap": "78,09", "e": "S", "st": "Eleito"}, {"seq": "2", "n": "22", "vap": "1668", "pvap": "21,91", "e": "N", "st": "N\u00e3o eleito"}]}, {"dt": "30/10/2022", "ht": "21:19:21", "tf": "S", "and": "F", "tpabr": "ZONA", "cdabr": "15", "s": "40", "st": "40", "snt": "0", "si": "40", "sni": "0", "sa": "40", "sna": "0", "pst": "100,00", "psnt": "0,00", "psi": "100,00", "psni": "0,00", "psa": "100,00", "psna": "0,00", "e": "11263", "ea": "11263", "ena": "0", "esi": "11263", "esni": "0", "a": "3410", "c": "7853", "pea": "100,00", "pena": "0,00", "pesi": "100,00", "pesni": "0,00", "pa": "30,28", "pc": "69,72", "vnom": "7612", "vscv": "0", "tv": "7853", "vvc": "7612", "vb": "70", "tvn": "171", "vn": "171", "vnt": "0", "vp": "0", "vv": "7612", "van": "0", "vansj": "0", "pvnom": "100,00", "pvvc": "96,93", "pvb": "0,89", "ptvn": "2,18", "pvn": "100,00", "pvnt": "0,00", "pvp": "0,00", "pvv": "100,00", "pvan": "0,00", "pvansj": "0,00", "cand": [{"seq": "1", "n": "13", "vap": "5944", "pvap": "78,09", "e": "S", "st": "Eleito"}, {"seq": "2", "n": "22", "vap": "1668", "pvap": "21,91", "e": "N", "st": "N\u00e3o eleito"}]}]}