{"ele": "545", "carper": "1", "md": "E", "t": "2", "f": "O", "esae": "N", "mnae": " ", "dg": "31/10/2022", "hg": "00:29:39", "dv": "S", "nadf": "mt-c0001-e000545-001-f", "abr": [{"dt": "30/10/2022", "ht": "18:10:12", "tf": "S", "and": "F", "tpabr": "MU", "cdabr": "90670", "s": "1275", "st": "1275", "snt": "0", "si": "1275", "sni": "0", "sa": "1275", "sna": "0", "pst": "100,00", "psnt": "0,00", "psi": "100,00", "psni": "0,00", "psa": "100,00", "psna": "0,00", "e": "428204", "ea": "428204", "ena": "0", "esi": "428204", "esni": "0", "c": "358003", "a": "70201", "pea": "100,00", "pena": "0,00", "pesi": "100,00", "pesni": "0,00", "pa": "16,39", "pc": "83,61", "vscv": "0", "vnom": "347639", "tv": "358003", "vvc": "347639", "vb": "3659", "tvn": "6705", "vn": "6705", "vnt": "0", "vp": "0", "vv": "347639", "van": "0", "vansj": "0", "pvnom": "100,00", "pvvc": "97,11", "pvb": "1,02", "ptvn": "1,87", "pvn": "100,00", "pvnt": "0,00", "pvp": "0,00", "pvv": "100,00", "pvan": "0,00", "pvansj": "0,00", "cand": [{"seq": "1", "n": "13", "vap": "133852", "pvap": "38,50", "e": "S", "st": "Eleito"}, {"seq": "2", "n": "22", "vap": "213787", "pvap": "61,50", "e": "N", "st": "N\u00e3o eleito"}]}, {"dt": "30/10/2022", "ht": "18:10:12", "tf": "S", "and": "P", "tpabr": "ZONA", "cdabr": "51", "s": "330", "st": "330", "snt": "0", "si": "330", "sni": "0", "sa": "330", "sna": "0", "pst": "100,00", "psnt": "0,00", "psi": "100,00", "psni": "0,00", "psa": "100,00", "psna": "0,00", "e": "114097", "ea": "114097", "ena": "0", "esi": "114097", "esni": "0", "a": "19072", "c": "95025", "pea": "100,00", "pena": "0,00", "pesi": "100,00", "pesni": "0,00", "pa": "16,72", "pc": "83,28", "vnom": "92297", "vscv": "0", "tv": "95025", "vvc": "92297", "vb": "933", "tvn": "1795", "vn": "1795", "vnt": "0", "vp": "0", "vv": "92297", "van": "0", "vansj": "0", "pvnom": "100,00", "pvvc": "97,13", "pvb": "0,98", "ptvn": "1,89", "pvn": "100,00", "pvnt": "0,00", "pvp": "0,00", "pvv": "100,00", "pvan": "0,00", "pvansj": "0,00", "cand": [{"seq": "1", "n": "13", "vap": "36888", "pvap": "39,97", "e": "S", "st": "Eleito"}, {"seq": "2", "n": "22", "vap": "55409", "pvap": "60,03", "e": "N", "st": "N\u00e3o eleito"}]}, {"dt": "30/10/2022", "ht": "18:10:12", "tf": "S", "and": "P", "tpabr": "ZONA", "cdabr": "1", "s": "312", "st": "312", "snt": "0", "si": "312", "sni": "0", "sa": "312", "sna": "0", "pst": "100,00", "psnt": "0,00", "psi": "100,00", "psni": "0,00", "psa": "100,00", "psna": "0,00", "e": "93896", "ea": "93896", "ena": "0", "esi": "93896", "esni": "0", "a": "14760", "c": "79136", "pea": "100,00", "pena": "0,00", "pesi": "100,00", "pesni": "0,00", "pa": "15,72", "pc": "84,28", "vnom": "77083", "vscv": "0", "tv": "79136", "vvc": "77083", "vb": "759", "tvn": "1294", "vn": "1294", "vnt": "0", "vp": "0", "vv": "77083", "van": "0", "vansj": "0", "pvnom": "100,00", "pvvc": "97,41", "pvb": "0,95", "ptvn": "1,64", "pvn": "100,00", "pvnt": "0,00", "pvp": "0,00", "pvv": "100,00", "pvan": "0,00", "pvansj": "0,00", "cand": [{"seq": "1", "n": "13", "vap": "25909", "pvap": "33,61", "e": "S", "st": "Eleito"}, {"seq": "2", "n": "22", "vap": "51174", "pvap": "66,39", "e": "N", "st": "N\u00e3o eleito"}]}, {"dt": "30/10/2022", "ht": "18:10:12", "tf": "S", "and": "P", "tpabr": "ZONA", "cdabr": "55", "s": "304", "st": "304", "snt": "0", "si": "304", "sni": "0", "sa": "304", "sna": "0", "pst": "100,00", "psnt": "0,00", "psi": "100,00", "psni": "0,00", "psa": "100,00", "psna": "0,00", "e": "111016", "ea": "111016", "ena": "0", "esi": "111016", "esni": "0", "a": "18941", "c": "92075", "pea": "100,00", "pena": "0,00", "pesi": "100,00", "pesni": "0,00", "pa": "17,06", "pc": "82,94", "vnom": "89155", "vscv": "0", "tv": "92075", "vvc": "89155", "vb": "1010", "tvn": "1910", "vn": "1910", "vnt": "0", "vp": "0", "vv": "89155", "van": "0", "vansj": "0", "pvnom": "100,00", "pvvc": "96,83", "pvb": "1,10", "ptvn": "2,07", "pvn": "100,00", "pvnt": "0,00", "pvp": "0,00", "pvv": "100,00", "pvan": "0,00", "pvansj": "0,00", "cand": [{"seq": "1", "n": "13", "vap": "36692", "pvap": "41,16", "e": "S", "st": "Eleito"}, {"seq": "2", "n": "22", "vap": "52463", "pvap": "58,84", "e": "N", "st": "N\u00e3o eleito"}]}, {"dt": "30/10/2022", "ht": "18:10:12", "tf": "S", "and": "P", "tpabr": "ZONA", "cdabr": "39", "s": "329", "st": "329", "snt": "0", "si": "329", "sni": "0", "sa": "329", "sna": "0", "pst": "100,00", "psnt": "0,00", "psi": "100,00", "psni": "0,00", "psa": "100,00", "psna": "0,00", "e": "109195", "ea": "109195", "ena": "0", "esi": "109195", "esni": "0", "a": "17428", "c": "91767", "pea": "100,00", "pena": "0,00", "pesi": "100,00", "pesni": "0,00", "pa": "15,96", "pc": "84,04", "vnom": "89104", "vscv": "0", "tv": "91767", "vvc": "89104", "vb": "957", "tvn": "1706", "vn": "1706", "vnt": "0", "vp": "0", "vv": "89104", "van": "0", "vansj": "0", "pvnom": "100,00", "pvvc": "97,10", "pvb": "1,04", "ptvn": "1,86", "pvn": "100,00", "pvnt": "0,00", "pvp": "0,00", "pvv": "100,00", "pvan": "0,00", "pvansj": "0,00", "cand": [{"seq": "1", "n": "13", "vap": "34363", "pvap": "38,57", "e": "S", "st": "Eleito"}, {"seq": "2", "n": "22", "vap": "54741", "pvap": "61,43", "e": "N", "st": "N\u00e3o eleito"}]}]}