{"ele": "545", "carper": "1", "md": "E", "t": "2", "f": "O", "esae": "N", "mnae": " ", "dg": "31/10/2022", "hg": "00:29:30", "dv": "S", "nadf": "pa-c0001-e000545-002-f", "abr": [{"dt": "30/10/2022", "ht": "18:57:07", "tf": "S", "and": "F", "tpabr": "MU", "cdabr": "04561", "s": "46", "st": "46", "snt": "0", "si": "46", "sni": "0", "sa": "46", "sna": "0", "pst": "100,00", "psnt": "0,00", "psi": "100,00", "psni": "0,00", "psa": "100,00", "psna": "0,00", "e": "14082", "ea": "14082", "ena": "0", "esi": "14082", "esni": "0", "c": "10551", "a": "3531", "pea": "100,00", "pena": "0,00", "pesi": "100,00", "pesni": "0,00", "pa": "25,07", "pc": "74,93", "vscv": "0", "vnom": "10337", "tv": "10551", "vvc": "10337", "vb": "58", "tvn": "156", "vn": "156", "vnt": "0", "vp": "0", "vv": "10337", "van": "0", "vansj": "0", "pvnom": "100,00", "pvvc": "97,97", "pvb": "0,55", "ptvn": "1,48", "pvn": "100,00", "pvnt": "0,00", "pvp": "0,00", "pvv": "100,00", "pvan": "0,00", "pvansj": "0,00", "cand": [{"seq": "1", "n": "13", "vap": "4802", "pvap": "46,45", "e": "S", "st": "Eleito"}, {"seq": "2", "n": "22", "vap": "5535", "pvap": "53,55", "e": "N", "st": "N\u00e3o eleito"}]}, {"dt": "30/10/2022", "ht": "18:57:07", "tf": "S", "and": "F", "tpabr": "ZONA", "cdabr": "24", "s": "46", "st": "46", "snt": "0", "si": "46", "sni": "0", "sa": "46", "sna": "0", "pst": "100,00", "psnt": "0,00", "psi": "100,00", "psni": "0,00", "psa": "100,00", "psna": "0,00", "e": "14082", "ea": "14082", "ena": "0", "esi": "14082", "esni": "0", "a": "3531", "c": "10551", "pea": "100,00", "pena": "0,00", "pesi": "100,00", "pesni": "0,00", "pa": "25,07", "pc": "74,93", "vnom": "10337", "vscv": "0", "tv": "10551", "vvc": "10337", "vb": "58", "tvn": "156", "vn": "156", "vnt": "0", "vp": "0", "vv": "10337", "van": "0", "vansj": "0", "pvnom": "100,00", "pvvc": "97,97", "pvb": "0,55", "ptvn": "1,48", "pvn": "100,00", "pvnt": "0,00", "pvp": "0,00", "pvv": "100,00", "pvan": "0,00", "pvansj": "0,00", "cand": [{"seq": "1", "n": "13", "vap": "4802", "pvap": "46,45", "e": "S", "st": "Eleito"}, {"seq": "2", "n": "22", "vap": "5535", "pvap": "53,55", "e": "N", "st": "N\u00e3o eleito"}]}]}