{"ele": "545", "carper": "1", "md": "E", "t": "2", "f": "O", "esae": "N", "mnae": " ", "dg": "31/10/2022", "hg": "00:29:32", "dv": "S", "nadf": "pe-c0001-e000545-001-f", "abr": [{"dt": "30/10/2022", "ht": "19:10:34", "tf": "S", "and": "F", "tpabr": "MU", "cdabr": "24830", "s": "36", "st": "36", "snt": "0", "si": "36", "sni": "0", "sa": "36", "sna": "0", "pst": "100,00", "psnt": "0,00", "psi": "100,00", "psni": "0,00", "psa": "100,00", "psna": "0,00", "e": "9408", "ea": "9408", "ena": "0", "esi": "9408", "esni": "0", "c": "6070", "a": "3338", "pea": "100,00", "pena": "0,00", "pesi": "100,00", "pesni": "0,00", "pa": "35,48", "pc": "64,52", "vscv": "0", "vnom": "5679", "tv": "6070", "vvc": "5679", "vb": "67", "tvn": "324", "vn": "324", "vnt": "0", "vp": "0", "vv": "5679", "van": "0", "vansj": "0", "pvnom": "100,00", "pvvc": "93,56", "pvb": "1,10", "ptvn": "5,34", "pvn": "100,00", "pvnt": "0,00", "pvp": "0,00", "pvv": "100,00", "pvan": "0,00", "pvansj": "0,00", "cand": [{"seq": "1", "n": "13", "vap": "4040", "pvap": "71,14", "e": "S", "st": "Eleito"}, {"seq": "2", "n": "22", "vap": "1639", "pvap": "28,86", "e": "N", "st": "N\u00e3o eleito"}]}, {"dt": "30/10/2022", "ht": "19:10:34", "tf": "S", "and": "F", "tpabr": "ZONA", "cdabr": "43", "s": "36", "st": "36", "snt": "0", "si": "36", "sni": "0", "sa": "36", "sna": "0", "pst": "100,00", "psnt": "0,00", "psi": "100,00", "psni": "0,00", "psa": "100,00", "psna": "0,00", "e": "9408", "ea": "9408", "ena": "0", "esi": "9408", "esni": "0", "a": "3338", "c": "6070", "pea": "100,00", "pena": "0,00", "pesi": "100,00", "pesni": "0,00", "pa": "35,48", "pc": "64,52", "vnom": "5679", "vscv": "0", "tv": "6070", "vvc": "5679", "vb": "67", "tvn": "324", "vn": "324", "vnt": "0", "vp": "0", "vv": "5679", "van": "0", "vansj": "0", "pvnom": "100,00", "pvvc": "93,56", "pvb": "1,10", "ptvn": "5,34", "pvn": "100,00", "pvnt": "0,00", "pvp": "0,00", "pvv": "100,00", "pvan": "0,00", "pvansj": "0,00", "cand": [{"seq": "1", "n": "13", "vap": "4040", "pvap": "71,14", "e": "S", "st": "Eleito"}, {"seq": "2", "n": "22", "vap": "1639", "pvap": "28,86", "e": "N", "st": "N\u00e3o eleito"}]}]}