{"ele": "545", "carper": "1", "md": "E", "t": "2", "f": "O", "esae": "N", "mnae": " ", "dg": "31/10/2022", "hg": "00:29:34", "dv": "S", "nadf": "pi-c0001-e000545-002-f", "abr": [{"dt": "30/10/2022", "ht": "19:00:13", "tf": "S", "and": "F", "tpabr": "MU", "cdabr": "10065", "s": "20", "st": "20", "snt": "0", "si": "20", "sni": "0", "sa": "20", "sna": "0", "pst": "100,00", "psnt": "0,00", "psi": "100,00", "psni": "0,00", "psa": "100,00", "psna": "0,00", "e": "6086", "ea": "6086", "ena": "0", "esi": "6086", "esni": "0", "c": "4974", "a": "1112", "pea": "100,00", "pena": "0,00", "pesi": "100,00", "pesni": "0,00", "pa": "18,27", "pc": "81,73", "vscv": "0", "vnom": "4812", "tv": "4974", "vvc": "4812", "vb": "53", "tvn": "109", "vn": "109", "vnt": "0", "vp": "0", "vv": "4812", "van": "0", "vansj": "0", "pvnom": "100,00", "pvvc": "96,74", "pvb": "1,07", "ptvn": "2,19", "pvn": "100,00", "pvnt": "0,00", "pvp": "0,00", "pvv": "100,00", "pvan": "0,00", "pvansj": "0,00", "cand": [{"seq": "1", "n": "13", "vap": "3789", "pvap": "78,74", "e": "S", "st": "Eleito"}, {"seq": "2", "n": "22", "vap": "1023", "pvap": "21,26", "e": "N", "st": "N\u00e3o eleito"}]}, {"dt": "30/10/2022", "ht": "19:00:13", "tf": "S", "and": "F", "tpabr": "ZONA", "cdabr": "33", "s": "20", "st": "20", "snt": "0", "si": "20", "sni": "0", "sa": "20", "sna": "0", "pst": "100,00", "psnt": "0,00", "psi": "100,00", "psni": "0,00", "psa": "100,00", "psna": "0,00", "e": "6086", "ea": "6086", "ena": "0", "esi": "6086", "esni": "0", "a": "1112", "c": "4974", "pea": "100,00", "pena": "0,00", "pesi": "100,00", "pesni": "0,00", "pa": "18,27", "pc": "81,73", "vnom": "4812", "vscv": "0", "tv": "4974", "vvc": "4812", "vb": "53", "tvn": "109", "vn": "109", "vnt": "0", "vp": "0", "vv": "4812", "van": "0", "vansj": "0", "pvnom": "100,00", "pvvc": "96,74", "pvb": "1,07", "ptvn": "2,19", "pvn": "100,00", "pvnt": "0,00", "pvp": "0,00", "pvv": "100,00", "pvan": "0,00", "pvansj": "0,00", "cand": [{"seq": "1", "n": "13", "vap": "3789", "pvap": "78,74", "e": "S", "st": "Eleito"}, {"seq": "2", "n": "22", "vap": "1023", "pvap": "21,26", "e": "N", "st": "N\u00e3o eleito"}]}]}