{"ele": "545", "carper": "1", "md": "E", "t": "2", "f": "O", "esae": "N", "mnae": " ", "dg": "31/10/2022", "hg": "00:29:34", "dv": "S", "nadf": "pi-c0001-e000545-002-f", "abr": [{"dt": "30/10/2022", "ht": "19:25:43", "tf": "S", "and": "F", "tpabr": "MU", "cdabr": "12521", "s": "9", "st": "9", "snt": "0", "si": "9", "sni": "0", "sa": "9", "sna": "0", "pst": "100,00", "psnt": "0,00", "psi": "100,00", "psni": "0,00", "psa": "100,00", "psna": "0,00", "e": "2418", "ea": "2418", "ena": "0", "esi": "2418", "esni": "0", "c": "1939", "a": "479", "pea": "100,00", "pena": "0,00", "pesi": "100,00", "pesni": "0,00", "pa": "19,81", "pc": "80,19", "vscv": "0", "vnom": "1850", "tv": "1939", "vvc": "1850", "vb": "15", "tvn": "74", "vn": "74", "vnt": "0", "vp": "0", "vv": "1850", "van": "0", "vansj": "0", "pvnom": "100,00", "pvvc": "95,41", "pvb": "0,77", "ptvn": "3,82", "pvn": "100,00", "pvnt": "0,00", "pvp": "0,00", "pvv": "100,00", "pvan": "0,00", "pvansj": "0,00", "cand": [{"seq": "1", "n": "13", "vap": "1524", "pvap": "82,38", "e": "S", "st": "Eleito"}, {"seq": "2", "n": "22", "vap": "326", "pvap": "17,62", "e": "N", "st": "N\u00e3o eleito"}]}, {"dt": "30/10/2022", "ht": "19:25:43", "tf": "S", "and": "F", "tpabr": "ZONA", "cdabr": "48", "s": "9", "st": "9", "snt": "0", "si": "9", "sni": "0", "sa": "9", "sna": "0", "pst": "100,00", "psnt": "0,00", "psi": "100,00", "psni": "0,00", "psa": "100,00", "psna": "0,00", "e": "2418", "ea": "2418", "ena": "0", "esi": "2418", "esni": "0", "a": "479", "c": "1939", "pea": "100,00", "pena": "0,00", "pesi": "100,00", "pesni": "0,00", "pa": "19,81", "pc": "80,19", "vnom": "1850", "vscv": "0", "tv": "1939", "vvc": "1850", "vb": "15", "tvn": "74", "vn": "74", "vnt": "0", "vp": "0", "vv": "1850", "van": "0", "vansj": "0", "pvnom": "100,00", "pvvc": "95,41", "pvb": "0,77", "ptvn": "3,82", "pvn": "100,00", "pvnt": "0,00", "pvp": "0,00", "pvv": "100,00", "pvan": "0,00", "pvansj": "0,00", "cand": [{"seq": "1", "n": "13", "vap": "1524", "pvap": "82,38", "e": "S", "st": "Eleito"}, {"seq": "2", "n": "22", "vap": "326", "pvap": "17,62", "e": "N", "st": "N\u00e3o eleito"}]}]}