{"ele": "545", "carper": "1", "md": "E", "t": "2", "f": "O", "esae": "N", "mnae": " ", "dg": "31/10/2022", "hg": "00:29:43", "dv": "S", "nadf": "pr-c0001-e000545-002-f", "abr": [{"dt": "30/10/2022", "ht": "18:20:34", "tf": "S", "and": "F", "tpabr": "MU", "cdabr": "76279", "s": "12", "st": "12", "snt": "0", "si": "12", "sni": "0", "sa": "12", "sna": "0", "pst": "100,00", "psnt": "0,00", "psi": "100,00", "psni": "0,00", "psa": "100,00", "psna": "0,00", "e": "4207", "ea": "4207", "ena": "0", "esi": "4207", "esni": "0", "c": "3543", "a": "664", "pea": "100,00", "pena": "0,00", "pesi": "100,00", "pesni": "0,00", "pa": "15,78", "pc": "84,22", "vscv": "0", "vnom": "3448", "tv": "3543", "vvc": "3448", "vb": "38", "tvn": "57", "vn": "57", "vnt": "0", "vp": "0", "vv": "3448", "van": "0", "vansj": "0", "pvnom": "100,00", "pvvc": "97,32", "pvb": "1,07", "ptvn": "1,61", "pvn": "100,00", "pvnt": "0,00", "pvp": "0,00", "pvv": "100,00", "pvan": "0,00", "pvansj": "0,00", "cand": [{"seq": "1", "n": "13", "vap": "1414", "pvap": "41,01", "e": "S", "st": "Eleito"}, {"seq": "2", "n": "22", "vap": "2034", "pvap": "58,99", "e": "N", "st": "N\u00e3o eleito"}]}, {"dt": "30/10/2022", "ht": "18:20:34", "tf": "S", "and": "F", "tpabr": "ZONA", "cdabr": "19", "s": "12", "st": "12", "snt": "0", "si": "12", "sni": "0", "sa": "12", "sna": "0", "pst": "100,00", "psnt": "0,00", "psi": "100,00", "psni": "0,00", "psa": "100,00", "psna": "0,00", "e": "4207", "ea": "4207", "ena": "0", "esi": "4207", "esni": "0", "a": "664", "c": "3543", "pea": "100,00", "pena": "0,00", "pesi": "100,00", "pesni": "0,00", "pa": "15,78", "pc": "84,22", "vnom": "3448", "vscv": "0", "tv": "3543", "vvc": "3448", "vb": "38", "tvn": "57", "vn": "57", "vnt": "0", "vp": "0", "vv": "3448", "van": "0", "vansj": "0", "pvnom": "100,00", "pvvc": "97,32", "pvb": "1,07", "ptvn": "1,61", "pvn": "100,00", "pvnt": "0,00", "pvp": "0,00", "pvv": "100,00", "pvan": "0,00", "pvansj": "0,00", "cand": [{"seq": "1", "n": "13", "vap": "1414", "pvap": "41,01", "e": "S", "st": "Eleito"}, {"seq": "2", "n": "22", "vap": "2034", "pvap": "58,99", "e": "N", "st": "N\u00e3o eleito"}]}]}