{"ele": "545", "carper": "1", "md": "E", "t": "2", "f": "O", "esae": "N", "mnae": " ", "dg": "31/10/2022", "hg": "00:29:55", "dv": "S", "nadf": "rn-c0001-e000545-001-f", "abr": [{"dt": "30/10/2022", "ht": "17:38:28", "tf": "S", "and": "F", "tpabr": "MU", "cdabr": "17094", "s": "34", "st": "34", "snt": "0", "si": "34", "sni": "0", "sa": "34", "sna": "0", "pst": "100,00", "psnt": "0,00", "psi": "100,00", "psni": "0,00", "psa": "100,00", "psna": "0,00", "e": "10485", "ea": "10485", "ena": "0", "esi": "10485", "esni": "0", "c": "8882", "a": "1603", "pea": "100,00", "pena": "0,00", "pesi": "100,00", "pesni": "0,00", "pa": "15,29", "pc": "84,71", "vscv": "0", "vnom": "8666", "tv": "8882", "vvc": "8666", "vb": "63", "tvn": "153", "vn": "153", "vnt": "0", "vp": "0", "vv": "8666", "van": "0", "vansj": "0", "pvnom": "100,00", "pvvc": "97,57", "pvb": "0,71", "ptvn": "1,72", "pvn": "100,00", "pvnt": "0,00", "pvp": "0,00", "pvv": "100,00", "pvan": "0,00", "pvansj": "0,00", "cand": [{"seq": "1", "n": "13", "vap": "7185", "pvap": "82,91", "e": "S", "st": "Eleito"}, {"seq": "2", "n": "22", "vap": "1481", "pvap": "17,09", "e": "N", "st": "N\u00e3o eleito"}]}, {"dt": "30/10/2022", "ht": "17:38:28", "tf": "S", "and": "F", "tpabr": "ZONA", "cdabr": "26", "s": "34", "st": "34", "snt": "0", "si": "34", "sni": "0", "sa": "34", "sna": "0", "pst": "100,00", "psnt": "0,00", "psi": "100,00", "psni": "0,00", "psa": "100,00", "psna": "0,00", "e": "10485", "ea": "10485", "ena": "0", "esi": "10485", "esni": "0", "a": "1603", "c": "8882", "pea": "100,00", "pena": "0,00", "pesi": "100,00", "pesni": "0,00", "pa": "15,29", "pc": "84,71", "vnom": "8666", "vscv": "0", "tv": "8882", "vvc": "8666", "vb": "63", "tvn": "153", "vn": "153", "vnt": "0", "vp": "0", "vv": "8666", "van": "0", "vansj": "0", "pvnom": "100,00", "pvvc": "97,57", "pvb": "0,71", "ptvn": "1,72", "pvn": "100,00", "pvnt": "0,00", "pvp": "0,00", "pvv": "100,00", "pvan": "0,00", "pvansj": "0,00", "cand": [{"seq": "1", "n": "13", "vap": "7185", "pvap": "82,91", "e": "S", "st": "Eleito"}, {"seq": "2", "n": "22", "vap": "1481", "pvap": "17,09", "e": "N", "st": "N\u00e3o eleito"}]}]}