{"ele": "545", "carper": "1", "md": "E", "t": "2", "f": "O", "esae": "N", "mnae": " ", "dg": "31/10/2022", "hg": "00:29:55", "dv": "S", "nadf": "rn-c0001-e000545-001-f", "abr": [{"dt": "30/10/2022", "ht": "17:43:52", "tf": "S", "and": "F", "tpabr": "MU", "cdabr": "18210", "s": "11", "st": "11", "snt": "0", "si": "11", "sni": "0", "sa": "11", "sna": "0", "pst": "100,00", "psnt": "0,00", "psi": "100,00", "psni": "0,00", "psa": "100,00", "psna": "0,00", "e": "4001", "ea": "4001", "ena": "0", "esi": "4001", "esni": "0", "c": "3293", "a": "708", "pea": "100,00", "pena": "0,00", "pesi": "100,00", "pesni": "0,00", "pa": "17,70", "pc": "82,30", "vscv": "0", "vnom": "3179", "tv": "3293", "vvc": "3179", "vb": "39", "tvn": "75", "vn": "75", "vnt": "0", "vp": "0", "vv": "3179", "van": "0", "vansj": "0", "pvnom": "100,00", "pvvc": "96,54", "pvb": "1,18", "ptvn": "2,28", "pvn": "100,00", "pvnt": "0,00", "pvp": "0,00", "pvv": "100,00", "pvan": "0,00", "pvansj": "0,00", "cand": [{"seq": "1", "n": "13", "vap": "2569", "pvap": "80,81", "e": "S", "st": "Eleito"}, {"seq": "2", "n": "22", "vap": "610", "pvap": "19,19", "e": "N", "st": "N\u00e3o eleito"}]}, {"dt": "30/10/2022", "ht": "17:43:52", "tf": "S", "and": "F", "tpabr": "ZONA", "cdabr": "40", "s": "11", "st": "11", "snt": "0", "si": "11", "sni": "0", "sa": "11", "sna": "0", "pst": "100,00", "psnt": "0,00", "psi": "100,00", "psni": "0,00", "psa": "100,00", "psna": "0,00", "e": "4001", "ea": "4001", "ena": "0", "esi": "4001", "esni": "0", "a": "708", "c": "3293", "pea": "100,00", "pena": "0,00", "pesi": "100,00", "pesni": "0,00", "pa": "17,70", "pc": "82,30", "vnom": "3179", "vscv": "0", "tv": "3293", "vvc": "3179", "vb": "39", "tvn": "75", "vn": "75", "vnt": "0", "vp": "0", "vv": "3179", "van": "0", "vansj": "0", "pvnom": "100,00", "pvvc": "96,54", "pvb": "1,18", "ptvn": "2,28", "pvn": "100,00", "pvnt": "0,00", "pvp": "0,00", "pvv": "100,00", "pvan": "0,00", "pvansj": "0,00", "cand": [{"seq": "1", "n": "13", "vap": "2569", "pvap": "80,81", "e": "S", "st": "Eleito"}, {"seq": "2", "n": "22", "vap": "610", "pvap": "19,19", "e": "N", "st": "N\u00e3o eleito"}]}]}