{"ele": "545", "carper": "1", "md": "E", "t": "2", "f": "O", "esae": "N", "mnae": " ", "dg": "31/10/2022", "hg": "00:29:35", "dv": "S", "nadf": "sp-c0001-e000545-187-f", "abr": [{"dt": "30/10/2022", "ht": "18:21:34", "tf": "S", "and": "F", "tpabr": "MU", "cdabr": "62634", "s": "38", "st": "38", "snt": "0", "si": "38", "sni": "0", "sa": "38", "sna": "0", "pst": "100,00", "psnt": "0,00", "psi": "100,00", "psni": "0,00", "psa": "100,00", "psna": "0,00", "e": "13666", "ea": "13666", "ena": "0", "esi": "13666", "esni": "0", "c": "10408", "a": "3258", "pea": "100,00", "pena": "0,00", "pesi": "100,00", "pesni": "0,00", "pa": "23,84", "pc": "76,16", "vscv": "0", "vnom": "9871", "tv": "10408", "vvc": "9871", "vb": "167", "tvn": "370", "vn": "370", "vnt": "0", "vp": "0", "vv": "9871", "van": "0", "vansj": "0", "pvnom": "100,00", "pvvc": "94,84", "pvb": "1,61", "ptvn": "3,55", "pvn": "100,00", "pvnt": "0,00", "pvp": "0,00", "pvv": "100,00", "pvan": "0,00", "pvansj": "0,00", "cand": [{"seq": "1", "n": "13", "vap": "3544", "pvap": "35,90", "e": "S", "st": "Eleito"}, {"seq": "2", "n": "22", "vap": "6327", "pvap": "64,10", "e": "N", "st": "N\u00e3o eleito"}]}, {"dt": "30/10/2022", "ht": "18:21:34", "tf": "S", "and": "F", "tpabr": "ZONA", "cdabr": "214", "s": "38", "st": "38", "snt": "0", "si": "38", "sni": "0", "sa": "38", "sna": "0", "pst": "100,00", "psnt": "0,00", "psi": "100,00", "psni": "0,00", "psa": "100,00", "psna": "0,00", "e": "13666", "ea": "13666", "ena": "0", "esi": "13666", "esni": "0", "a": "3258", "c": "10408", "pea": "100,00", "pena": "0,00", "pesi": "100,00", "pesni": "0,00", "pa": "23,84", "pc": "76,16", "vnom": "9871", "vscv": "0", "tv": "10408", "vvc": "9871", "vb": "167", "tvn": "370", "vn": "370", "vnt": "0", "vp": "0", "vv": "9871", "van": "0", "vansj": "0", "pvnom": "100,00", "pvvc": "94,84", "pvb": "1,61", "ptvn": "3,55", "pvn": "100,00", "pvnt": "0,00", "pvp": "0,00", "pvv": "100,00", "pvan": "0,00", "pvansj": "0,00", "cand": [{"seq": "1", "n": "13", "vap": "3544", "pvap": "35,90", "e": "S", "st": "Eleito"}, {"seq": "2", "n": "22", "vap": "6327", "pvap": "64,10", "e": "N", "st": "N\u00e3o eleito"}]}]}