{"ele": "545", "carper": "1", "md": "E", "t": "2", "f": "O", "esae": "N", "mnae": " ", "dg": "31/10/2022", "hg": "00:29:36", "dv": "S", "nadf": "sp-c0001-e000545-187-f", "abr": [{"dt": "30/10/2022", "ht": "18:19:22", "tf": "S", "and": "F", "tpabr": "MU", "cdabr": "71277", "s": "9", "st": "9", "snt": "0", "si": "9", "sni": "0", "sa": "9", "sna": "0", "pst": "100,00", "psnt": "0,00", "psi": "100,00", "psni": "0,00", "psa": "100,00", "psna": "0,00", "e": "3019", "ea": "3019", "ena": "0", "esi": "3019", "esni": "0", "c": "2431", "a": "588", "pea": "100,00", "pena": "0,00", "pesi": "100,00", "pesni": "0,00", "pa": "19,48", "pc": "80,52", "vscv": "0", "vnom": "2304", "tv": "2431", "vvc": "2304", "vb": "45", "tvn": "82", "vn": "82", "vnt": "0", "vp": "0", "vv": "2304", "van": "0", "vansj": "0", "pvnom": "100,00", "pvvc": "94,78", "pvb": "1,85", "ptvn": "3,37", "pvn": "100,00", "pvnt": "0,00", "pvp": "0,00", "pvv": "100,00", "pvan": "0,00", "pvansj": "0,00", "cand": [{"seq": "1", "n": "13", "vap": "789", "pvap": "34,24", "e": "S", "st": "Eleito"}, {"seq": "2", "n": "22", "vap": "1515", "pvap": "65,76", "e": "N", "st": "N\u00e3o eleito"}]}, {"dt": "30/10/2022", "ht": "18:19:22", "tf": "S", "and": "F", "tpabr": "ZONA", "cdabr": "77", "s": "9", "st": "9", "snt": "0", "si": "9", "sni": "0", "sa": "9", "sna": "0", "pst": "100,00", "psnt": "0,00", "psi": "100,00", "psni": "0,00", "psa": "100,00", "psna": "0,00", "e": "3019", "ea": "3019", "ena": "0", "esi": "3019", "esni": "0", "a": "588", "c": "2431", "pea": "100,00", "pena": "0,00", "pesi": "100,00", "pesni": "0,00", "pa": "19,48", "pc": "80,52", "vnom": "2304", "vscv": "0", "tv": "2431", "vvc": "2304", "vb": "45", "tvn": "82", "vn": "82", "vnt": "0", "vp": "0", "vv": "2304", "van": "0", "vansj": "0", "pvnom": "100,00", "pvvc": "94,78", "pvb": "1,85", "ptvn": "3,37", "pvn": "100,00", "pvnt": "0,00", "pvp": "0,00", "pvv": "100,00", "pvan": "0,00", "pvansj": "0,00", "cand": [{"seq": "1", "n": "13", "vap": "789", "pvap": "34,24", "e": "S", "st": "Eleito"}, {"seq": "2", "n": "22", "vap": "1515", "pvap": "65,76", "e": "N", "st": "N\u00e3o eleito"}]}]}