{"ele": "544", "carper": "1", "md": "S", "t": "1", "f": "O", "esae": "N", "mnae": " ", "dg": "04/10/2022", "hg": "12:07:41", "dv": "S", "nadf": "am-c0001-e000544-005-f", "abr": [{"dt": "02/10/2022", "ht": "18:10:06", "tf": "S", "and": "F", "tpabr": "MU", "cdabr": "02020", "s": "34", "st": "34", "snt": "0", "si": "34", "sni": "0", "sa": "34", "sna": "0", "pst": "100,00", "psnt": "0,00", "psi": "100,00", "psni": "0,00", "psa": "100,00", "psna": "0,00", "e": "11815", "ea": "11815", "ena": "0", "esi": "11815", "esni": "0", "c": "7977", "a": "3838", "pea": "100,00", "pena": "0,00", "pesi": "100,00", "pesni": "0,00", "pa": "32,48", "pc": "67,52", "vscv": "0", "vnom": "7760", "tv": "7977", "vvc": "7760", "vb": "45", "tvn": "172", "vn": "172", "vnt": "0", "vp": "0", "vv": "7760", "van": "0", "vansj": "0", "pvnom": "100,00", "pvvc": "97,28", "pvb": "0,56", "ptvn": "2,16", "pvn": "100,00", "pvnt": "0,00", "pvp": "0,00", "pvv": "100,00", "pvan": "0,00", "pvansj": "0,00", "cand": [{"seq": "7", "n": "14", "vap": "4", "pvap": "0,05", "e": "N", "st": "N\u00e3o eleito"}, {"seq": "9", "n": "21", "vap": "5", "pvap": "0,06", "e": "N", "st": "N\u00e3o eleito"}, {"seq": "4", "n": "12", "vap": "141", "pvap": "1,82", "e": "N", "st": "N\u00e3o eleito"}, {"seq": "8", "n": "80", "vap": "1", "pvap": "0,01", "e": "N", "st": "N\u00e3o eleito"}, {"seq": "3", "n": "15", "vap": "242", "pvap": "3,12", "e": "N", "st": "N\u00e3o eleito"}, {"seq": "5", "n": "44", "vap": "74", "pvap": "0,95", "e": "N", "st": "N\u00e3o eleito"}, {"seq": "6", "n": "30", "vap": "4", "pvap": "0,05", "e": "N", "st": "N\u00e3o eleito"}, {"seq": "1", "n": "13", "vap": "3135", "pvap": "40,40", "e": "S", "st": "2\u00ba turno"}, {"seq": "2", "n": "22", "vap": "4154", "pvap": "53,53", "e": "S", "st": "2\u00ba turno"}, {"seq": "10", "n": "16", "vap": "0", "pvap": "00,00", "e": "N", "st": "N\u00e3o eleito"}, {"seq": "11", "n": "27", "vap": "0", "pvap": "00,00", "e": "N", "st": "N\u00e3o eleito"}]}, {"dt": "02/10/2022", "ht": "18:10:06", "tf": "S", "and": "F", "tpabr": "ZONA", "cdabr": "45", "s": "34", "st": "34", "snt": "0", "si": "34", "sni": "0", "sa": "34", "sna": "0", "pst": "100,00", "psnt": "0,00", "psi": "100,00", "psni": "0,00", "psa": "100,00", "psna": "0,00", "e": "11815", "ea": "11815", "ena": "0", "esi": "11815", "esni": "0", "a": "3838", "c": "7977", "pea": "100,00", "pena": "0,00", "pesi": "100,00", "pesni": "0,00", "pa": "32,48", "pc": "67,52", "vnom": "7760", "vscv": "0", "tv": "7977", "vvc": "7760", "vb": "45", "tvn": "172", "vn": "172", "vnt": "0", "vp": "0", "vv": "7760", "van": "0", "vansj": "0", "pvnom": "100,00", "pvvc": "97,28", "pvb": "0,56", "ptvn": "2,16", "pvn": "100,00", "pvnt": "0,00", "pvp": "0,00", "pvv": "100,00", "pvan": "0,00", "pvansj": "0,00", "cand": [{"seq": "1", "n": "13", "vap": "3135", "pvap": "40,40", "e": "S", "st": "2\u00ba turno"}, {"seq": "2", "n": "22", "vap": "4154", "pvap": "53,53", "e": "S", "st": "2\u00ba turno"}, {"seq": "3", "n": "15", "vap": "242", "pvap": "3,12", "e": "N", "st": "N\u00e3o eleito"}, {"seq": "4", "n": "12", "vap": "141", "pvap": "1,82", "e": "N", "st": "N\u00e3o eleito"}, {"seq": "5", "n": "44", "vap": "74", "pvap": "0,95", "e": "N", "st": "N\u00e3o eleito"}, {"seq": "6", "n": "30", "vap": "4", "pvap": "0,05", "e": "N", "st": "N\u00e3o eleito"}, {"seq": "7", "n": "14", "vap": "4", "pvap": "0,05", "e": "N", "st": "N\u00e3o eleito"}, {"seq": "8", "n": "80", "vap": "1", "pvap": "0,01", "e": "N", "st": "N\u00e3o eleito"}, {"seq": "9", "n": "21", "vap": "5", "pvap": "0,06", "e": "N", "st": "N\u00e3o eleito"}]}]}