{"ele": "544", "carper": "1", "md": "S", "t": "1", "f": "O", "esae": "N", "mnae": " ", "dg": "04/10/2022", "hg": "12:07:20", "dv": "S", "nadf": "ba-c0001-e000544-005-f", "abr": [{"dt": "02/10/2022", "ht": "20:25:55", "tf": "S", "and": "F", "tpabr": "MU", "cdabr": "39691", "s": "51", "st": "51", "snt": "0", "si": "51", "sni": "0", "sa": "51", "sna": "0", "pst": "100,00", "psnt": "0,00", "psi": "100,00", "psni": "0,00", "psa": "100,00", "psna": "0,00", "e": "16867", "ea": "16867", "ena": "0", "esi": "16867", "esni": "0", "c": "12656", "a": "4211", "pea": "100,00", "pena": "0,00", "pesi": "100,00", "pesni": "0,00", "pa": "24,97", "pc": "75,03", "vscv": "0", "vnom": "12100", "tv": "12656", "vvc": "12100", "vb": "133", "tvn": "423", "vn": "423", "vnt": "0", "vp": "0", "vv": "12100", "van": "0", "vansj": "0", "pvnom": "100,00", "pvvc": "95,61", "pvb": "1,05", "ptvn": "3,34", "pvn": "100,00", "pvnt": "0,00", "pvp": "0,00", "pvv": "100,00", "pvan": "0,00", "pvansj": "0,00", "cand": [{"seq": "2", "n": "22", "vap": "2981", "pvap": "24,64", "e": "S", "st": "2\u00ba turno"}, {"seq": "8", "n": "21", "vap": "3", "pvap": "0,02", "e": "N", "st": "N\u00e3o eleito"}, {"seq": "6", "n": "30", "vap": "1", "pvap": "0,01", "e": "N", "st": "N\u00e3o eleito"}, {"seq": "5", "n": "44", "vap": "158", "pvap": "1,31", "e": "N", "st": "N\u00e3o eleito"}, {"seq": "1", "n": "13", "vap": "8412", "pvap": "69,52", "e": "S", "st": "2\u00ba turno"}, {"seq": "7", "n": "14", "vap": "9", "pvap": "0,07", "e": "N", "st": "N\u00e3o eleito"}, {"seq": "9", "n": "80", "vap": "1", "pvap": "0,01", "e": "N", "st": "N\u00e3o eleito"}, {"seq": "3", "n": "12", "vap": "240", "pvap": "1,98", "e": "N", "st": "N\u00e3o eleito"}, {"seq": "10", "n": "16", "vap": "3", "pvap": "0,02", "e": "N", "st": "N\u00e3o eleito"}, {"seq": "11", "n": "27", "vap": "1", "pvap": "0,01", "e": "N", "st": "N\u00e3o eleito"}, {"seq": "4", "n": "15", "vap": "291", "pvap": "2,40", "e": "N", "st": "N\u00e3o eleito"}]}, {"dt": "02/10/2022", "ht": "20:25:55", "tf": "S", "and": "F", "tpabr": "ZONA", "cdabr": "197", "s": "51", "st": "51", "snt": "0", "si": "51", "sni": "0", "sa": "51", "sna": "0", "pst": "100,00", "psnt": "0,00", "psi": "100,00", "psni": "0,00", "psa": "100,00", "psna": "0,00", "e": "16867", "ea": "16867", "ena": "0", "esi": "16867", "esni": "0", "a": "4211", "c": "12656", "pea": "100,00", "pena": "0,00", "pesi": "100,00", "pesni": "0,00", "pa": "24,97", "pc": "75,03", "vnom": "12100", "vscv": "0", "tv": "12656", "vvc": "12100", "vb": "133", "tvn": "423", "vn": "423", "vnt": "0", "vp": "0", "vv": "12100", "van": "0", "vansj": "0", "pvnom": "100,00", "pvvc": "95,61", "pvb": "1,05", "ptvn": "3,34", "pvn": "100,00", "pvnt": "0,00", "pvp": "0,00", "pvv": "100,00", "pvan": "0,00", "pvansj": "0,00", "cand": [{"seq": "1", "n": "13", "vap": "8412", "pvap": "69,52", "e": "S", "st": "2\u00ba turno"}, {"seq": "2", "n": "22", "vap": "2981", "pvap": "24,64", "e": "S", "st": "2\u00ba turno"}, {"seq": "3", "n": "12", "vap": "240", "pvap": "1,98", "e": "N", "st": "N\u00e3o eleito"}, {"seq": "4", "n": "15", "vap": "291", "pvap": "2,40", "e": "N", "st": "N\u00e3o eleito"}, {"seq": "5", "n": "44", "vap": "158", "pvap": "1,31", "e": "N", "st": "N\u00e3o eleito"}, {"seq": "6", "n": "30", "vap": "1", "pvap": "0,01", "e": "N", "st": "N\u00e3o eleito"}, {"seq": "7", "n": "14", "vap": "9", "pvap": "0,07", "e": "N", "st": "N\u00e3o eleito"}, {"seq": "8", "n": "21", "vap": "3", "pvap": "0,02", "e": "N", "st": "N\u00e3o eleito"}, {"seq": "9", "n": "80", "vap": "1", "pvap": "0,01", "e": "N", "st": "N\u00e3o eleito"}, {"seq": "10", "n": "16", "vap": "3", "pvap": "0,02", "e": "N", "st": "N\u00e3o eleito"}, {"seq": "11", "n": "27", "vap": "1", "pvap": "0,01", "e": "N", "st": "N\u00e3o eleito"}]}]}