{"ele": "544", "carper": "1", "md": "S", "t": "1", "f": "O", "esae": "N", "mnae": " ", "dg": "04/10/2022", "hg": "12:07:50", "dv": "S", "nadf": "mg-c0001-e000544-005-f", "abr": [{"dt": "02/10/2022", "ht": "20:53:28", "tf": "S", "and": "F", "tpabr": "MU", "cdabr": "45519", "s": "31", "st": "31", "snt": "0", "si": "31", "sni": "0", "sa": "31", "sna": "0", "pst": "100,00", "psnt": "0,00", "psi": "100,00", "psni": "0,00", "psa": "100,00", "psna": "0,00", "e": "10568", "ea": "10568", "ena": "0", "esi": "10568", "esni": "0", "c": "7900", "a": "2668", "pea": "100,00", "pena": "0,00", "pesi": "100,00", "pesni": "0,00", "pa": "25,25", "pc": "74,75", "vscv": "0", "vnom": "7429", "tv": "7900", "vvc": "7429", "vb": "154", "tvn": "317", "vn": "317", "vnt": "0", "vp": "0", "vv": "7429", "van": "0", "vansj": "0", "pvnom": "100,00", "pvvc": "94,04", "pvb": "1,95", "ptvn": "4,01", "pvn": "100,00", "pvnt": "0,00", "pvp": "0,00", "pvv": "100,00", "pvan": "0,00", "pvansj": "0,00", "cand": [{"seq": "9", "n": "21", "vap": "2", "pvap": "0,03", "e": "N", "st": "N\u00e3o eleito"}, {"seq": "5", "n": "30", "vap": "34", "pvap": "0,46", "e": "N", "st": "N\u00e3o eleito"}, {"seq": "4", "n": "12", "vap": "154", "pvap": "2,07", "e": "N", "st": "N\u00e3o eleito"}, {"seq": "7", "n": "14", "vap": "5", "pvap": "0,07", "e": "N", "st": "N\u00e3o eleito"}, {"seq": "2", "n": "22", "vap": "1878", "pvap": "25,28", "e": "S", "st": "2\u00ba turno"}, {"seq": "11", "n": "27", "vap": "3", "pvap": "0,04", "e": "N", "st": "N\u00e3o eleito"}, {"seq": "1", "n": "13", "vap": "5053", "pvap": "68,02", "e": "S", "st": "2\u00ba turno"}, {"seq": "10", "n": "16", "vap": "2", "pvap": "0,03", "e": "N", "st": "N\u00e3o eleito"}, {"seq": "6", "n": "44", "vap": "20", "pvap": "0,27", "e": "N", "st": "N\u00e3o eleito"}, {"seq": "3", "n": "15", "vap": "275", "pvap": "3,70", "e": "N", "st": "N\u00e3o eleito"}, {"seq": "8", "n": "80", "vap": "3", "pvap": "0,04", "e": "N", "st": "N\u00e3o eleito"}]}, {"dt": "02/10/2022", "ht": "20:53:28", "tf": "S", "and": "F", "tpabr": "ZONA", "cdabr": "101", "s": "31", "st": "31", "snt": "0", "si": "31", "sni": "0", "sa": "31", "sna": "0", "pst": "100,00", "psnt": "0,00", "psi": "100,00", "psni": "0,00", "psa": "100,00", "psna": "0,00", "e": "10568", "ea": "10568", "ena": "0", "esi": "10568", "esni": "0", "a": "2668", "c": "7900", "pea": "100,00", "pena": "0,00", "pesi": "100,00", "pesni": "0,00", "pa": "25,25", "pc": "74,75", "vnom": "7429", "vscv": "0", "tv": "7900", "vvc": "7429", "vb": "154", "tvn": "317", "vn": "317", "vnt": "0", "vp": "0", "vv": "7429", "van": "0", "vansj": "0", "pvnom": "100,00", "pvvc": "94,04", "pvb": "1,95", "ptvn": "4,01", "pvn": "100,00", "pvnt": "0,00", "pvp": "0,00", "pvv": "100,00", "pvan": "0,00", "pvansj": "0,00", "cand": [{"seq": "1", "n": "13", "vap": "5053", "pvap": "68,02", "e": "S", "st": "2\u00ba turno"}, {"seq": "2", "n": "22", "vap": "1878", "pvap": "25,28", "e": "S", "st": "2\u00ba turno"}, {"seq": "3", "n": "15", "vap": "275", "pvap": "3,70", "e": "N", "st": "N\u00e3o eleito"}, {"seq": "4", "n": "12", "vap": "154", "pvap": "2,07", "e": "N", "st": "N\u00e3o eleito"}, {"seq": "5", "n": "30", "vap": "34", "pvap": "0,46", "e": "N", "st": "N\u00e3o eleito"}, {"seq": "6", "n": "44", "vap": "20", "pvap": "0,27", "e": "N", "st": "N\u00e3o eleito"}, {"seq": "7", "n": "14", "vap": "5", "pvap": "0,07", "e": "N", "st": "N\u00e3o eleito"}, {"seq": "8", "n": "80", "vap": "3", "pvap": "0,04", "e": "N", "st": "N\u00e3o eleito"}, {"seq": "9", "n": "21", "vap": "2", "pvap": "0,03", "e": "N", "st": "N\u00e3o eleito"}, {"seq": "10", "n": "16", "vap": "2", "pvap": "0,03", "e": "N", "st": "N\u00e3o eleito"}, {"seq": "11", "n": "27", "vap": "3", "pvap": "0,04", "e": "N", "st": "N\u00e3o eleito"}]}]}