{"ele": "544", "carper": "1", "md": "S", "t": "1", "f": "O", "esae": "N", "mnae": " ", "dg": "04/10/2022", "hg": "12:07:20", "dv": "S", "nadf": "rs-c0001-e000544-005-f", "abr": [{"dt": "02/10/2022", "ht": "19:46:32", "tf": "S", "and": "F", "tpabr": "MU", "cdabr": "86070", "s": "14", "st": "14", "snt": "0", "si": "14", "sni": "0", "sa": "14", "sna": "0", "pst": "100,00", "psnt": "0,00", "psi": "100,00", "psni": "0,00", "psa": "100,00", "psna": "0,00", "e": "3688", "ea": "3688", "ena": "0", "esi": "3688", "esni": "0", "c": "3182", "a": "506", "pea": "100,00", "pena": "0,00", "pesi": "100,00", "pesni": "0,00", "pa": "13,72", "pc": "86,28", "vscv": "0", "vnom": "3047", "tv": "3182", "vvc": "3047", "vb": "95", "tvn": "40", "vn": "40", "vnt": "0", "vp": "0", "vv": "3047", "van": "0", "vansj": "0", "pvnom": "100,00", "pvvc": "95,76", "pvb": "2,98", "ptvn": "1,26", "pvn": "100,00", "pvnt": "0,00", "pvp": "0,00", "pvv": "100,00", "pvan": "0,00", "pvansj": "0,00", "cand": [{"seq": "7", "n": "14", "vap": "6", "pvap": "0,20", "e": "N", "st": "N\u00e3o eleito"}, {"seq": "4", "n": "12", "vap": "48", "pvap": "1,58", "e": "N", "st": "N\u00e3o eleito"}, {"seq": "2", "n": "13", "vap": "1258", "pvap": "41,29", "e": "S", "st": "2\u00ba turno"}, {"seq": "5", "n": "30", "vap": "7", "pvap": "0,23", "e": "N", "st": "N\u00e3o eleito"}, {"seq": "1", "n": "22", "vap": "1556", "pvap": "51,07", "e": "S", "st": "2\u00ba turno"}, {"seq": "6", "n": "44", "vap": "5", "pvap": "0,16", "e": "N", "st": "N\u00e3o eleito"}, {"seq": "3", "n": "15", "vap": "167", "pvap": "5,48", "e": "N", "st": "N\u00e3o eleito"}, {"seq": "9", "n": "80", "vap": "0", "pvap": "00,00", "e": "N", "st": "N\u00e3o eleito"}, {"seq": "11", "n": "27", "vap": "0", "pvap": "00,00", "e": "N", "st": "N\u00e3o eleito"}, {"seq": "10", "n": "16", "vap": "0", "pvap": "00,00", "e": "N", "st": "N\u00e3o eleito"}, {"seq": "8", "n": "21", "vap": "0", "pvap": "00,00", "e": "N", "st": "N\u00e3o eleito"}]}, {"dt": "02/10/2022", "ht": "19:46:32", "tf": "S", "and": "F", "tpabr": "ZONA", "cdabr": "138", "s": "14", "st": "14", "snt": "0", "si": "14", "sni": "0", "sa": "14", "sna": "0", "pst": "100,00", "psnt": "0,00", "psi": "100,00", "psni": "0,00", "psa": "100,00", "psna": "0,00", "e": "3688", "ea": "3688", "ena": "0", "esi": "3688", "esni": "0", "a": "506", "c": "3182", "pea": "100,00", "pena": "0,00", "pesi": "100,00", "pesni": "0,00", "pa": "13,72", "pc": "86,28", "vnom": "3047", "vscv": "0", "tv": "3182", "vvc": "3047", "vb": "95", "tvn": "40", "vn": "40", "vnt": "0", "vp": "0", "vv": "3047", "van": "0", "vansj": "0", "pvnom": "100,00", "pvvc": "95,76", "pvb": "2,98", "ptvn": "1,26", "pvn": "100,00", "pvnt": "0,00", "pvp": "0,00", "pvv": "100,00", "pvan": "0,00", "pvansj": "0,00", "cand": [{"seq": "1", "n": "22", "vap": "1556", "pvap": "51,07", "e": "S", "st": "2\u00ba turno"}, {"seq": "2", "n": "13", "vap": "1258", "pvap": "41,29", "e": "S", "st": "2\u00ba turno"}, {"seq": "3", "n": "15", "vap": "167", "pvap": "5,48", "e": "N", "st": "N\u00e3o eleito"}, {"seq": "4", "n": "12", "vap": "48", "pvap": "1,58", "e": "N", "st": "N\u00e3o eleito"}, {"seq": "5", "n": "30", "vap": "7", "pvap": "0,23", "e": "N", "st": "N\u00e3o eleito"}, {"seq": "6", "n": "44", "vap": "5", "pvap": "0,16", "e": "N", "st": "N\u00e3o eleito"}, {"seq": "7", "n": "14", "vap": "6", "pvap": "0,20", "e": "N", "st": "N\u00e3o eleito"}]}]}