{"ele": "544", "carper": "1", "md": "S", "t": "1", "f": "O", "esae": "N", "mnae": " ", "dg": "04/10/2022", "hg": "12:07:28", "dv": "S", "nadf": "se-c0001-e000544-005-f", "abr": [{"dt": "02/10/2022", "ht": "19:26:31", "tf": "S", "and": "F", "tpabr": "MU", "cdabr": "32212", "s": "31", "st": "31", "snt": "0", "si": "31", "sni": "0", "sa": "31", "sna": "0", "pst": "100,00", "psnt": "0,00", "psi": "100,00", "psni": "0,00", "psa": "100,00", "psna": "0,00", "e": "8615", "ea": "8615", "ena": "0", "esi": "8615", "esni": "0", "c": "6753", "a": "1862", "pea": "100,00", "pena": "0,00", "pesi": "100,00", "pesni": "0,00", "pa": "21,61", "pc": "78,39", "vscv": "0", "vnom": "6421", "tv": "6753", "vvc": "6421", "vb": "93", "tvn": "239", "vn": "239", "vnt": "0", "vp": "0", "vv": "6421", "van": "0", "vansj": "0", "pvnom": "100,00", "pvvc": "95,08", "pvb": "1,38", "ptvn": "3,54", "pvn": "100,00", "pvnt": "0,00", "pvp": "0,00", "pvv": "100,00", "pvan": "0,00", "pvansj": "0,00", "cand": [{"seq": "3", "n": "15", "vap": "157", "pvap": "2,45", "e": "N", "st": "N\u00e3o eleito"}, {"seq": "8", "n": "16", "vap": "1", "pvap": "0,02", "e": "N", "st": "N\u00e3o eleito"}, {"seq": "4", "n": "12", "vap": "254", "pvap": "3,96", "e": "N", "st": "N\u00e3o eleito"}, {"seq": "7", "n": "14", "vap": "3", "pvap": "0,05", "e": "N", "st": "N\u00e3o eleito"}, {"seq": "9", "n": "80", "vap": "1", "pvap": "0,02", "e": "N", "st": "N\u00e3o eleito"}, {"seq": "1", "n": "13", "vap": "4579", "pvap": "71,31", "e": "S", "st": "2\u00ba turno"}, {"seq": "2", "n": "22", "vap": "1399", "pvap": "21,79", "e": "S", "st": "2\u00ba turno"}, {"seq": "6", "n": "30", "vap": "8", "pvap": "0,12", "e": "N", "st": "N\u00e3o eleito"}, {"seq": "5", "n": "44", "vap": "19", "pvap": "0,30", "e": "N", "st": "N\u00e3o eleito"}, {"seq": "10", "n": "21", "vap": "0", "pvap": "00,00", "e": "N", "st": "N\u00e3o eleito"}, {"seq": "11", "n": "27", "vap": "0", "pvap": "00,00", "e": "N", "st": "N\u00e3o eleito"}]}, {"dt": "02/10/2022", "ht": "19:26:31", "tf": "S", "and": "F", "tpabr": "ZONA", "cdabr": "14", "s": "31", "st": "31", "snt": "0", "si": "31", "sni": "0", "sa": "31", "sna": "0", "pst": "100,00", "psnt": "0,00", "psi": "100,00", "psni": "0,00", "psa": "100,00", "psna": "0,00", "e": "8615", "ea": "8615", "ena": "0", "esi": "8615", "esni": "0", "a": "1862", "c": "6753", "pea": "100,00", "pena": "0,00", "pesi": "100,00", "pesni": "0,00", "pa": "21,61", "pc": "78,39", "vnom": "6421", "vscv": "0", "tv": "6753", "vvc": "6421", "vb": "93", "tvn": "239", "vn": "239", "vnt": "0", "vp": "0", "vv": "6421", "van": "0", "vansj": "0", "pvnom": "100,00", "pvvc": "95,08", "pvb": "1,38", "ptvn": "3,54", "pvn": "100,00", "pvnt": "0,00", "pvp": "0,00", "pvv": "100,00", "pvan": "0,00", "pvansj": "0,00", "cand": [{"seq": "4", "n": "12", "vap": "254", "pvap": "3,96", "e": "N", "st": "N\u00e3o eleito"}, {"seq": "1", "n": "13", "vap": "4579", "pvap": "71,31", "e": "S", "st": "2\u00ba turno"}, {"seq": "7", "n": "14", "vap": "3", "pvap": "0,05", "e": "N", "st": "N\u00e3o eleito"}, {"seq": "3", "n": "15", "vap": "157", "pvap": "2,45", "e": "N", "st": "N\u00e3o eleito"}, {"seq": "8", "n": "16", "vap": "1", "pvap": "0,02", "e": "N", "st": "N\u00e3o eleito"}, {"seq": "2", "n": "22", "vap": "1399", "pvap": "21,79", "e": "S", "st": "2\u00ba turno"}, {"seq": "6", "n": "30", "vap": "8", "pvap": "0,12", "e": "N", "st": "N\u00e3o eleito"}, {"seq": "5", "n": "44", "vap": "19", "pvap": "0,30", "e": "N", "st": "N\u00e3o eleito"}, {"seq": "9", "n": "80", "vap": "1", "pvap": "0,02", "e": "N", "st": "N\u00e3o eleito"}]}]}