{"ele": "544", "carper": "1", "md": "S", "t": "1", "f": "O", "esae": "N", "mnae": " ", "dg": "04/10/2022", "hg": "12:07:27", "dv": "S", "nadf": "se-c0001-e000544-005-f", "abr": [{"dt": "02/10/2022", "ht": "19:59:58", "tf": "S", "and": "F", "tpabr": "MU", "cdabr": "32050", "s": "27", "st": "27", "snt": "0", "si": "27", "sni": "0", "sa": "27", "sna": "0", "pst": "100,00", "psnt": "0,00", "psi": "100,00", "psni": "0,00", "psa": "100,00", "psna": "0,00", "e": "8338", "ea": "8338", "ena": "0", "esi": "8338", "esni": "0", "c": "6338", "a": "2000", "pea": "100,00", "pena": "0,00", "pesi": "100,00", "pesni": "0,00", "pa": "23,99", "pc": "76,01", "vscv": "0", "vnom": "6068", "tv": "6338", "vvc": "6068", "vb": "111", "tvn": "159", "vn": "159", "vnt": "0", "vp": "0", "vv": "6068", "van": "0", "vansj": "0", "pvnom": "100,00", "pvvc": "95,74", "pvb": "1,75", "ptvn": "2,51", "pvn": "100,00", "pvnt": "0,00", "pvp": "0,00", "pvv": "100,00", "pvan": "0,00", "pvansj": "0,00", "cand": [{"seq": "3", "n": "15", "vap": "175", "pvap": "2,88", "e": "N", "st": "N\u00e3o eleito"}, {"seq": "6", "n": "30", "vap": "10", "pvap": "0,16", "e": "N", "st": "N\u00e3o eleito"}, {"seq": "7", "n": "14", "vap": "3", "pvap": "0,05", "e": "N", "st": "N\u00e3o eleito"}, {"seq": "8", "n": "16", "vap": "1", "pvap": "0,02", "e": "N", "st": "N\u00e3o eleito"}, {"seq": "5", "n": "44", "vap": "24", "pvap": "0,40", "e": "N", "st": "N\u00e3o eleito"}, {"seq": "4", "n": "12", "vap": "174", "pvap": "2,87", "e": "N", "st": "N\u00e3o eleito"}, {"seq": "1", "n": "13", "vap": "4218", "pvap": "69,51", "e": "S", "st": "2\u00ba turno"}, {"seq": "2", "n": "22", "vap": "1462", "pvap": "24,09", "e": "S", "st": "2\u00ba turno"}, {"seq": "9", "n": "80", "vap": "1", "pvap": "0,02", "e": "N", "st": "N\u00e3o eleito"}, {"seq": "10", "n": "21", "vap": "0", "pvap": "00,00", "e": "N", "st": "N\u00e3o eleito"}, {"seq": "11", "n": "27", "vap": "0", "pvap": "00,00", "e": "N", "st": "N\u00e3o eleito"}]}, {"dt": "02/10/2022", "ht": "19:59:58", "tf": "S", "and": "F", "tpabr": "ZONA", "cdabr": "11", "s": "27", "st": "27", "snt": "0", "si": "27", "sni": "0", "sa": "27", "sna": "0", "pst": "100,00", "psnt": "0,00", "psi": "100,00", "psni": "0,00", "psa": "100,00", "psna": "0,00", "e": "8338", "ea": "8338", "ena": "0", "esi": "8338", "esni": "0", "a": "2000", "c": "6338", "pea": "100,00", "pena": "0,00", "pesi": "100,00", "pesni": "0,00", "pa": "23,99", "pc": "76,01", "vnom": "6068", "vscv": "0", "tv": "6338", "vvc": "6068", "vb": "111", "tvn": "159", "vn": "159", "vnt": "0", "vp": "0", "vv": "6068", "van": "0", "vansj": "0", "pvnom": "100,00", "pvvc": "95,74", "pvb": "1,75", "ptvn": "2,51", "pvn": "100,00", "pvnt": "0,00", "pvp": "0,00", "pvv": "100,00", "pvan": "0,00", "pvansj": "0,00", "cand": [{"seq": "4", "n": "12", "vap": "174", "pvap": "2,87", "e": "N", "st": "N\u00e3o eleito"}, {"seq": "1", "n": "13", "vap": "4218", "pvap": "69,51", "e": "S", "st": "2\u00ba turno"}, {"seq": "7", "n": "14", "vap": "3", "pvap": "0,05", "e": "N", "st": "N\u00e3o eleito"}, {"seq": "3", "n": "15", "vap": "175", "pvap": "2,88", "e": "N", "st": "N\u00e3o eleito"}, {"seq": "8", "n": "16", "vap": "1", "pvap": "0,02", "e": "N", "st": "N\u00e3o eleito"}, {"seq": "2", "n": "22", "vap": "1462", "pvap": "24,09", "e": "S", "st": "2\u00ba turno"}, {"seq": "6", "n": "30", "vap": "10", "pvap": "0,16", "e": "N", "st": "N\u00e3o eleito"}, {"seq": "5", "n": "44", "vap": "24", "pvap": "0,40", "e": "N", "st": "N\u00e3o eleito"}, {"seq": "9", "n": "80", "vap": "1", "pvap": "0,02", "e": "N", "st": "N\u00e3o eleito"}]}]}